{
  "timestamp": "2017-12-20T16:34:41+01:00",
  "specVersion": 0,
  "shopId": "610",
  "date": "2017-12-11",
  "closed": null,
  "meals": [
    {
      "mealId": 61,
      "currentlyAvailable": true,
      "description": {
        "DE": "Brokkolicremsuppe",
        "EN": null
      },
      "dispositionId": 61,
      "dispositionDescription": {
        "DE": "Suppe",
        "EN": null
      },
      "recommendedOrdering": 2,
      "ingredients": [
        "23",
        "26",
        "34W"
      ],
      "characterization": [
        "van",
        "bio"
      ],
      "imgUrlPathSuffix": null,
      "specialTimeWindow": [
        1130,
        1345
      ],
      "price": {
        "1": 1.8,
        "2": 2.25,
        "3": 3.2,
        "4": 5.6
      },
      "nutritionInformation": null
    }
  ]
}
